qt_module_manager/__init__.py
qt_module_manager-0.0.2.dist-info/LICENSE
qt_module_manager-0.0.2.dist-info/METADATA
qt_module_manager-0.0.2.dist-info/WHEEL
qt_module_manager-0.0.2.dist-info/top_level.txt
qt_module_manager-0.0.2.dist-info/RECORD
