Metadata-Version: 2.1
Name: qt-module-manager
Version: 0.0.2
Summary: A Qt module manager to view and reload the imported Python modules
Author: Hannes Delbeke
License: MIT License
Project-URL: Source, https://github.com/hannesdelbeke/qt-module-manager
Keywords: module,imported,reload,qt,pyside,widget,manager
Classifier: Programming Language :: Python :: 3.7
Requires-Python: >=3.4
License-File: LICENSE
Requires-Dist: qtpy
Requires-Dist: importlib-metadata ; python_version < "3.7"
